tomato/__init__.py
tomato/drivers.py
tomato/models.py
tomato/daemon/__init__.py
tomato/daemon/cmd.py
tomato/daemon/driver.py
tomato/daemon/io.py
tomato/daemon/job.py
tomato/daemon/jobdb.py
tomato/data/default_devices.json
tomato/driverinterface_1_0/__init__.py
tomato/driverinterface_2_0/__init__.py
tomato/driverinterface_2_1/__init__.py
tomato/driverinterface_2_1/decorators.py
tomato/driverinterface_2_1/types.py
tomato/ketchup/__init__.py
tomato/passata/__init__.py
tomato/tomato/__init__.py
tomato-2.1.dist-info/licenses/LICENSE
tomato-2.1.dist-info/METADATA
tomato-2.1.dist-info/WHEEL
tomato-2.1.dist-info/entry_points.txt
tomato-2.1.dist-info/top_level.txt
tomato-2.1.dist-info/RECORD
