Metadata-Version: 2.4
Name: tomato
Version: 2.1
Summary: au-tomation without pain
Author: Peter Kraus, Graham Kimbell
Maintainer-email: Peter Kraus <peter.kraus@tu-berlin.de>
Project-URL: Documentation, https://dgbowl.github.io/tomato/main
Project-URL: Issues, https://github.com/dgbowl/tomato/issues
Project-URL: Repository, https://github.com/dgbowl/tomato/
Classifier: Development Status :: 4 - Beta
Classifier: License :: OSI Approved :: GNU General Public License v3 or later (GPLv3+)
Classifier: Programming Language :: Python :: 3.10
Classifier: Programming Language :: Python :: 3.11
Classifier: Programming Language :: Python :: 3.12
Classifier: Programming Language :: Python :: 3.13
Classifier: Operating System :: OS Independent
Requires-Python: >=3.10
License-File: LICENSE
Requires-Dist: appdirs>=1.4.0
Requires-Dist: toml>=0.10
Requires-Dist: pyyaml>=6.0
Requires-Dist: psutil>=5.9
Requires-Dist: dgbowl_schemas>=124
Requires-Dist: pyzmq>=25.1
Requires-Dist: netcdf4>=1.7
Requires-Dist: xarray>=2024.10.0
Requires-Dist: pydantic>=2.0
Requires-Dist: pint>=0.24.1
Provides-Extra: testing
Requires-Dist: pytest; extra == "testing"
Requires-Dist: tomato-example-counter>=2.0.0; extra == "testing"
Requires-Dist: tomato-psutil>=1.0.0; extra == "testing"
Provides-Extra: docs
Requires-Dist: sphinx~=7.2; extra == "docs"
Requires-Dist: sphinx-rtd-theme~=1.3.0; extra == "docs"
Requires-Dist: autodoc-pydantic~=2.1; extra == "docs"
Requires-Dist: sphinxcontrib-mermaid~=0.9.2; extra == "docs"
Dynamic: license-file
